count_web_content/__init__.py
count_web_content/count_web_content.py
count_web_content-0.1.3.dist-info/METADATA
count_web_content-0.1.3.dist-info/WHEEL
count_web_content-0.1.3.dist-info/RECORD
